libnum/__init__.py
libnum/chains/__init__.py
libnum/chains/chain.py
libnum/chains/sqrt.py
libnum/common.py
libnum/compat.py
libnum/ecc.py
libnum/factorize.py
libnum/modular.py
libnum/primes.py
libnum/ranges.py
libnum/sqrtmod.py
libnum/strings.py
libnum/stuff.py
libnum-1.6.1.dist-info/WHEEL
libnum-1.6.1.dist-info/METADATA
libnum-1.6.1.dist-info/RECORD
